setup.py
dnsseccheck/__init__.py
dnsseccheck/dnsdict.py
dnsseccheck/dnssecchecks.py
dnsseccheck.egg-info/PKG-INFO
dnsseccheck.egg-info/SOURCES.txt
dnsseccheck.egg-info/dependency_links.txt
dnsseccheck.egg-info/entry_points.txt
dnsseccheck.egg-info/requires.txt
dnsseccheck.egg-info/top_level.txt