Metadata-Version: 1.0
Name: dnsseccheck
Version: 0.0.2
Summary: Analyze DNSSEC configuration of a Zone and validate it against best current practises
Home-page: https://github.com/gryphius/dnssecscore_backend
Author: O. Schacher
Author-email: oli@fuglu.org
License: UNKNOWN
Platform: UNKNOWN
